<annotation>
	<folder>gambar siap label</folder>
	<filename>073.png</filename>
	<path>F:\ghozy\gambar siap label-20210517T140800Z-001\gambar siap label\073.png</path>
	<source>
		<database>Unknown</database>
	</source>
	<size>
		<width>500</width>
		<height>500</height>
		<depth>3</depth>
	</size>
	<segmented>0</segmented>
	<object>
		<name>semblance</name>
		<pose>Unspecified</pose>
		<truncated>1</truncated>
		<difficult>0</difficult>
		<bndbox>
			<xmin>1</xmin>
			<ymin>3</ymin>
			<xmax>136</xmax>
			<ymax>26</ymax>
		</bndbox>
	</object>
	<object>
		<name>semblance</name>
		<pose>Unspecified</pose>
		<truncated>1</truncated>
		<difficult>0</difficult>
		<bndbox>
			<xmin>1</xmin>
			<ymin>43</ymin>
			<xmax>144</xmax>
			<ymax>75</ymax>
		</bndbox>
	</object>
	<object>
		<name>semblance</name>
		<pose>Unspecified</pose>
		<truncated>1</truncated>
		<difficult>0</difficult>
		<bndbox>
			<xmin>1</xmin>
			<ymin>84</ymin>
			<xmax>165</xmax>
			<ymax>105</ymax>
		</bndbox>
	</object>
	<object>
		<name>semblance</name>
		<pose>Unspecified</pose>
		<truncated>0</truncated>
		<difficult>0</difficult>
		<bndbox>
			<xmin>17</xmin>
			<ymin>116</ymin>
			<xmax>179</xmax>
			<ymax>158</ymax>
		</bndbox>
	</object>
	<object>
		<name>semblance</name>
		<pose>Unspecified</pose>
		<truncated>0</truncated>
		<difficult>0</difficult>
		<bndbox>
			<xmin>51</xmin>
			<ymin>163</ymin>
			<xmax>212</xmax>
			<ymax>184</ymax>
		</bndbox>
	</object>
	<object>
		<name>semblance</name>
		<pose>Unspecified</pose>
		<truncated>0</truncated>
		<difficult>0</difficult>
		<bndbox>
			<xmin>83</xmin>
			<ymin>196</ymin>
			<xmax>244</xmax>
			<ymax>226</ymax>
		</bndbox>
	</object>
	<object>
		<name>semblance</name>
		<pose>Unspecified</pose>
		<truncated>0</truncated>
		<difficult>0</difficult>
		<bndbox>
			<xmin>127</xmin>
			<ymin>236</ymin>
			<xmax>297</xmax>
			<ymax>255</ymax>
		</bndbox>
	</object>
	<object>
		<name>semblance</name>
		<pose>Unspecified</pose>
		<truncated>0</truncated>
		<difficult>0</difficult>
		<bndbox>
			<xmin>177</xmin>
			<ymin>267</ymin>
			<xmax>348</xmax>
			<ymax>308</ymax>
		</bndbox>
	</object>
	<object>
		<name>semblance</name>
		<pose>Unspecified</pose>
		<truncated>0</truncated>
		<difficult>0</difficult>
		<bndbox>
			<xmin>235</xmin>
			<ymin>313</ymin>
			<xmax>385</xmax>
			<ymax>332</ymax>
		</bndbox>
	</object>
	<object>
		<name>semblance</name>
		<pose>Unspecified</pose>
		<truncated>0</truncated>
		<difficult>0</difficult>
		<bndbox>
			<xmin>276</xmin>
			<ymin>347</ymin>
			<xmax>448</xmax>
			<ymax>385</ymax>
		</bndbox>
	</object>
	<object>
		<name>semblance</name>
		<pose>Unspecified</pose>
		<truncated>0</truncated>
		<difficult>0</difficult>
		<bndbox>
			<xmin>320</xmin>
			<ymin>391</ymin>
			<xmax>481</xmax>
			<ymax>413</ymax>
		</bndbox>
	</object>
	<object>
		<name>semblance</name>
		<pose>Unspecified</pose>
		<truncated>1</truncated>
		<difficult>0</difficult>
		<bndbox>
			<xmin>363</xmin>
			<ymin>444</ymin>
			<xmax>500</xmax>
			<ymax>476</ymax>
		</bndbox>
	</object>
</annotation>
